[
  {
    "code": "002379.SZ",
    "name": "宏创控股"
  },
  {
    "code": "000603.SZ",
    "name": "盛达资源"
  },
  {
    "code": "000426.SZ",
    "name": "兴业银锡"
  },
  {
    "code": "603527.SH",
    "name": "众源新材"
  },
  {
    "code": "000807.SZ",
    "name": "云铝股份"
  },
  {
    "code": "003038.SZ",
    "name": "鑫铂股份"
  },
  {
    "code": "603271.SH",
    "name": "永杰新材"
  },
  {
    "code": "002988.SZ",
    "name": "豪美新材"
  },
  {
    "code": "002532.SZ",
    "name": "天山铝业"
  },
  {
    "code": "601168.SH",
    "name": "西部矿业"
  },
  {
    "code": "600595.SH",
    "name": "中孚实业"
  },
  {
    "code": "603937.SH",
    "name": "丽岛新材"
  },
  {
    "code": "603045.SH",
    "name": "福达合金"
  },
  {
    "code": "002160.SZ",
    "name": "常铝股份"
  },
  {
    "code": "600961.SH",
    "name": "株冶集团"
  },
  {
    "code": "000933.SZ",
    "name": "神火股份"
  },
  {
    "code": "601899.SH",
    "name": "紫金矿业"
  },
  {
    "code": "000630.SZ",
    "name": "铜陵有色"
  },
  {
    "code": "002996.SZ",
    "name": "顺博合金"
  },
  {
    "code": "601600.SH",
    "name": "中国铝业"
  },
  {
    "code": "002203.SZ",
    "name": "海亮股份"
  },
  {
    "code": "600362.SH",
    "name": "江西铜业"
  },
  {
    "code": "002978.SZ",
    "name": "安宁股份"
  },
  {
    "code": "603978.SH",
    "name": "深圳新星"
  },
  {
    "code": "603876.SH",
    "name": "鼎胜新材"
  },
  {
    "code": "600531.SH",
    "name": "豫光金铅"
  },
  {
    "code": "600768.SH",
    "name": "宁波富邦"
  },
  {
    "code": "600219.SH",
    "name": "南山铝业"
  },
  {
    "code": "000612.SZ",
    "name": "焦作万方"
  },
  {
    "code": "000758.SZ",
    "name": "中色股份"
  },
  {
    "code": "600497.SH",
    "name": "驰宏锌锗"
  },
  {
    "code": "000878.SZ",
    "name": "云南铜业"
  },
  {
    "code": "601609.SH",
    "name": "金田股份"
  },
  {
    "code": "000060.SZ",
    "name": "中金岭南"
  },
  {
    "code": "601137.SH",
    "name": "博威合金"
  },
  {
    "code": "000737.SZ",
    "name": "北方铜业"
  },
  {
    "code": "002182.SZ",
    "name": "宝武镁业"
  },
  {
    "code": "002295.SZ",
    "name": "精艺股份"
  },
  {
    "code": "603132.SH",
    "name": "金徽股份"
  },
  {
    "code": "601212.SH",
    "name": "白银有色"
  },
  {
    "code": "601677.SH",
    "name": "明泰铝业"
  },
  {
    "code": "601702.SH",
    "name": "华峰铝业"
  },
  {
    "code": "000751.SZ",
    "name": "锌业股份"
  },
  {
    "code": "002171.SZ",
    "name": "楚江新材"
  },
  {
    "code": "600361.SH",
    "name": "创新新材"
  },
  {
    "code": "600888.SH",
    "name": "新疆众和"
  },
  {
    "code": "600490.SH",
    "name": "鹏欣资源"
  },
  {
    "code": "600255.SH",
    "name": "鑫科材料"
  },
  {
    "code": "002501.SZ",
    "name": "利源股份"
  },
  {
    "code": "600331.SH",
    "name": "宏达股份"
  },
  {
    "code": "601388.SH",
    "name": "怡球资源"
  },
  {
    "code": "002578.SZ",
    "name": "闽发铝业"
  },
  {
    "code": "002824.SZ",
    "name": "和胜股份"
  },
  {
    "code": "600338.SH",
    "name": "西藏珠峰"
  },
  {
    "code": "601020.SH",
    "name": "华钰矿业"
  },
  {
    "code": "002540.SZ",
    "name": "亚太科技"
  },
  {
    "code": "000633.SZ",
    "name": "合金投资"
  },
  {
    "code": "000688.SZ",
    "name": "国城矿业"
  },
  {
    "code": "002114.SZ",
    "name": "罗平锌电"
  }
]